{
  "filename": "file_31_1",
  "output": [
    {
      "class": "other",
      "gt": [],
      "pred": []
    },
    {
      "class": "PERSON",
      "gt": [],
      "pred": []
    },
    {
      "class": "DISEASE",
      "gt": [
        [
          42,
          449,
          72,
          458,
          "vermiculite"
        ],
        [
          158,
          449,
          170,
          458,
          "cold"
        ],
        [
          73,
          449,
          99,
          458,
          "insulation"
        ],
        [
          132,
          449,
          156,
          458,
          "common"
        ],
        [
          131,
          449,
          156,
          458,
          "asbestos"
        ]
      ],
      "pred": [
        [
          42,
          449,
          72,
          458,
          "vermiculite"
        ],
        [
          158,
          449,
          170,
          458,
          "cold"
        ],
        [
          73,
          449,
          99,
          458,
          "insulation"
        ],
        [
          132,
          449,
          156,
          458,
          "common"
        ],
        [
          131,
          449,
          156,
          458,
          "asbestos"
        ]
      ]
    },
    {
      "class": "CHEMICAL",
      "gt": [],
      "pred": []
    },
    {
      "class": "DOSAGE",
      "gt": [],
      "pred": []
    }
  ]
}